README.rst
setup.py
uniontypes/__init__.py
uniontypes.egg-info/PKG-INFO
uniontypes.egg-info/SOURCES.txt
uniontypes.egg-info/dependency_links.txt
uniontypes.egg-info/requires.txt
uniontypes.egg-info/top_level.txt
uniontypes/tests/__init__.py
uniontypes/tests/test_optiontypes.py
uniontypes/tests/test_uniontypes.py