Metadata-Version: 1.1
Name: uniontypes
Version: 0.1.0
Summary: Union types for python
Home-page: https://github.com/llllllllll/uniontypes
Author: Joe Jevnik
Author-email: joejev@gmail.com
License: GPL-2
Platform: UNKNOWN
Classifier: Development Status :: 3 - Alpha
Classifier: License :: OSI Approved :: GNU General Public License v2 (GPLv2)
Classifier: Natural Language :: English
Classifier: Programming Language :: Python :: 3.4
Classifier: Programming Language :: Python :: 3 :: Only
Classifier: Operating System :: POSIX
Classifier: Topic :: Software Development
